{
  "canvas": {
    "version": "2.2.11",
    "width": 2000,
    "height": 2000,
    "scrollTop": -230.33333333333337,
    "scrollLeft": -199.66666666666663,
    "zoomLevel": 1,
    "show": {
      "tableComment": true,
      "columnComment": true,
      "columnDataType": true,
      "columnDefault": true,
      "columnAutoIncrement": false,
      "columnPrimaryKey": true,
      "columnUnique": false,
      "columnNotNull": true,
      "relationship": true
    },
    "database": "MySQL",
    "databaseName": "",
    "canvasType": "@vuerd/builtin-sql-ddl",
    "language": "GraphQL",
    "tableCase": "pascalCase",
    "columnCase": "camelCase",
    "highlightTheme": "VS2015",
    "bracketType": "none",
    "setting": {
      "relationshipDataTypeSync": true,
      "relationshipOptimization": false,
      "columnOrder": [
        "columnName",
        "columnDataType",
        "columnNotNull",
        "columnUnique",
        "columnAutoIncrement",
        "columnDefault",
        "columnComment"
      ]
    },
    "pluginSerializationMap": {}
  },
  "table": {
    "tables": [
      {
        "name": "users",
        "comment": "",
        "columns": [
          {
            "name": "id",
            "comment": "",
            "dataType": "INT",
            "default": "",
            "option": {
              "autoIncrement": true,
              "primaryKey": true,
              "unique": false,
              "notNull": true
            },
            "ui": {
              "active": false,
              "pk": true,
              "fk": false,
              "pfk": false,
              "widthName": 60,
              "widthComment": 60,
              "widthDataType": 60,
              "widthDefault": 60
            },
            "id": "6fad7d48-78e5-4b66-b345-b315f9968ccc"
          },
          {
            "name": "created_at",
            "comment": "",
            "dataType": "timestamp",
            "default": "",
            "option": {
              "autoIncrement": false,
              "primaryKey": false,
              "unique": false,
              "notNull": true
            },
            "ui": {
              "active": false,
              "pk": false,
              "fk": false,
              "pfk": false,
              "widthName": 67.0634765625,
              "widthComment": 60,
              "widthDataType": 61.9599609375,
              "widthDefault": 60
            },
            "id": "6768fdae-29e0-45aa-a395-19875dd8d657"
          },
          {
            "name": "updated_at",
            "comment": "",
            "dataType": "timestamp",
            "default": "",
            "option": {
              "autoIncrement": false,
              "primaryKey": false,
              "unique": false,
              "notNull": true
            },
            "ui": {
              "active": false,
              "pk": false,
              "fk": false,
              "pfk": false,
              "widthName": 60,
              "widthComment": 60,
              "widthDataType": 60,
              "widthDefault": 60
            },
            "id": "23d03fc1-717a-4062-a512-7c966c047065"
          },
          {
            "name": "first_name",
            "comment": "",
            "dataType": "VARCHAR(255)",
            "default": "",
            "option": {
              "autoIncrement": false,
              "primaryKey": false,
              "unique": false,
              "notNull": true
            },
            "ui": {
              "active": false,
              "pk": false,
              "fk": false,
              "pfk": false,
              "widthName": 62.68994140625,
              "widthComment": 60,
              "widthDataType": 94.955078125,
              "widthDefault": 60
            },
            "id": "8052f6c7-84b8-44fd-b059-64f849cb276b"
          },
          {
            "name": "last_name",
            "comment": "",
            "dataType": "VARCHAR(255)",
            "default": "",
            "option": {
              "autoIncrement": false,
              "primaryKey": false,
              "unique": false,
              "notNull": true
            },
            "ui": {
              "active": false,
              "pk": false,
              "fk": false,
              "pfk": false,
              "widthName": 61.97900390625,
              "widthComment": 60,
              "widthDataType": 94.955078125,
              "widthDefault": 60
            },
            "id": "b75b5154-3ea8-4f10-8157-867f8d622526"
          }
        ],
        "ui": {
          "active": false,
          "left": 283.6667,
          "top": 269.3333,
          "zIndex": 57,
          "widthName": 60,
          "widthComment": 60
        },
        "visible": true,
        "id": "725962bb-3af1-4455-b2a7-a1f34320d7c2"
      },
      {
        "name": "friendships",
        "comment": "",
        "columns": [
          {
            "name": "friend_id",
            "comment": "",
            "dataType": "INT",
            "default": "",
            "option": {
              "autoIncrement": true,
              "primaryKey": true,
              "unique": false,
              "notNull": true
            },
            "ui": {
              "active": false,
              "pk": true,
              "fk": false,
              "pfk": false,
              "widthName": 60,
              "widthComment": 60,
              "widthDataType": 60,
              "widthDefault": 60
            },
            "id": "eebc8be4-fe9b-4310-94cb-4b20243ff144"
          },
          {
            "name": "created_at",
            "comment": "",
            "dataType": "timestamp",
            "default": "",
            "option": {
              "autoIncrement": false,
              "primaryKey": false,
              "unique": false,
              "notNull": true
            },
            "ui": {
              "active": false,
              "pk": false,
              "fk": false,
              "pfk": false,
              "widthName": 67.0634765625,
              "widthComment": 60,
              "widthDataType": 61.9599609375,
              "widthDefault": 60
            },
            "id": "8dfed180-6d8b-4671-80cd-12a3c0bcc940"
          },
          {
            "name": "updated_at",
            "comment": "",
            "dataType": "timestamp",
            "default": "",
            "option": {
              "autoIncrement": false,
              "primaryKey": false,
              "unique": false,
              "notNull": true
            },
            "ui": {
              "active": false,
              "pk": false,
              "fk": false,
              "pfk": false,
              "widthName": 60,
              "widthComment": 60,
              "widthDataType": 60,
              "widthDefault": 60
            },
            "id": "981a0d22-c01e-4a55-b0ca-b9ba5c227bf2"
          },
          {
            "name": "user_id",
            "comment": "",
            "dataType": "INT",
            "default": "",
            "option": {
              "autoIncrement": false,
              "primaryKey": false,
              "unique": false,
              "notNull": true
            },
            "ui": {
              "active": false,
              "pk": false,
              "fk": true,
              "pfk": false,
              "widthName": 60,
              "widthComment": 60,
              "widthDataType": 60,
              "widthDefault": 60
            },
            "id": "b607f0c0-812d-4e25-9732-1254c35b487d"
          }
        ],
        "ui": {
          "active": true,
          "left": 592.6667,
          "top": 712.3333,
          "zIndex": 76,
          "widthName": 64.8671875,
          "widthComment": 60
        },
        "visible": true,
        "id": "fc5335cf-c26a-48b2-b0a8-c06099828f1f"
      }
    ],
    "indexes": []
  },
  "memo": {
    "memos": []
  },
  "relationship": {
    "relationships": [
      {
        "identification": false,
        "relationshipType": "OneN",
        "startRelationshipType": "Dash",
        "start": {
          "tableId": "725962bb-3af1-4455-b2a7-a1f34320d7c2",
          "columnIds": [
            "6fad7d48-78e5-4b66-b345-b315f9968ccc"
          ],
          "x": 478.17597734375,
          "y": 440.8333,
          "direction": "bottom"
        },
        "end": {
          "tableId": "fc5335cf-c26a-48b2-b0a8-c06099828f1f",
          "columnIds": [
            "b607f0c0-812d-4e25-9732-1254c35b487d"
          ],
          "x": 592.6667,
          "y": 787.8333,
          "direction": "left"
        },
        "constraintName": "fk_users_to_friendships",
        "visible": true,
        "id": "b0a0f97e-1259-4900-9b1d-80f50cdb1ca1"
      }
    ]
  }
}